[
  {
    "project": "District Officials Training Seminar",
    "name": "Oathkeeper",
    "chair": "PP Rtr.| Rtn. Sayantonee Maitra",
    "date": "Jun 26th - 27th, 2021",
    "poster": true,
    "completed": true
  },
  {
    "project": "PETS SETS TETS",
    "name": "Anuborton",
    "chair": "PP Rtr. Debmalya Ghosh",
    "date": "Jul 2nd - 4th, 2021",
    "poster": true,
    "completed": true
  },
  {
    "project": "District Assembly",
    "name": "Montage",
    "chair": "IPP Rtr. Souradeep Banik",
    "date": "Aug 28th - 29th, 2021",
    "poster": true,
    "completed": null
  },
  {
    "project": "District Installation",
    "name": "Poriborton",
    "chair": "PP Rtr. Tanmoy Banik",
    "date": "Sep 5th, 2021",
    "poster": true,
    "completed": null
  },
  {
    "project": "Rotaract 3291 MUN",
    "name": "",
    "chair": "IPP Rtr. Shrobana Sengupta",
    "date": "Sep 25th - 27th, 2021",
    "poster": true,
    "completed": null
  },
  {
    "project": "Rotary Rotaract Sharod Swikriti",
    "name": "",
    "chair": "PP Rtr. Shaon Kundu",
    "date": "",
    "poster": null,
    "completed": null
  },
  {
    "project": "Yaas Relief",
    "name": "",
    "chair": "IPP Rtr. Rahul Saha",
    "date": "",
    "poster": null,
    "completed": null
  },
  {
    "project": "Rota Bangla Summit",
    "name": "",
    "chair": "PP Rtr. Subhranil Halder",
    "date": "",
    "poster": null,
    "completed": null
  },
  {
    "project": "Eye Surgery",
    "name": "",
    "chair": "PP Rtr.|Rtn. Soumitra Majumder",
    "date": "",
    "poster": null,
    "completed": null
  },
  {
    "project": "Nivedan",
    "name": "",
    "chair": "PP Rtr. Arinda Sarkar",
    "date": "",
    "poster": null,
    "completed": null
  },
  {
    "project": "DRR's Charity Fortnight",
    "name": "",
    "chair": "IPP Rtr. Swarnava Gan",
    "date": "",
    "poster": null,
    "completed": null
  },
  {
    "project": "District Conference",
    "name": "",
    "chair": "PP Rtr. Tanmoy Banik",
    "date": "",
    "poster": null,
    "completed": null
  },
  {
    "project": "Rota Sports Carnival (Rota Soccer, Rota Cricket, E-Sports & Others)",
    "name": "",
    "chair": "IPP Rtr. Gourab Dutta",
    "date": "",
    "poster": null,
    "completed": null
  },
  {
    "project": "District Picnic",
    "name": "",
    "chair": "PP Rtr. Sayandeep Chakraborty",
    "date": "",
    "poster": null,
    "completed": null
  },
  {
    "project": "Rota Excursion - Camp",
    "name": "",
    "chair": "PP Rtr. Saptarshi Gangopadhyay",
    "date": "",
    "poster": null,
    "completed": null
  },
  {
    "project": "Rota Week",
    "name": "",
    "chair": "PP Rtr. Supratim Sarkar",
    "date": "",
    "poster": null,
    "completed": null
  },
  {
    "project": "Rainbow",
    "name": "",
    "chair": "IPP Rtr. Adrija Ghosh",
    "date": "",
    "poster": null,
    "completed": null
  },
  {
    "project": "District Awards",
    "name": "",
    "chair": "PP Rtr.| Rtn. Shayan Dutta",
    "date": "",
    "poster": null,
    "completed": null
  }
 ]